Metadata-Version: 2.1
Name: phone-number-validator-lksl2jg
Version: 0.1.0
Summary: 
Author: Felipe
Author-email: 104157442+justafewwords4@users.noreply.github.com
Requires-Python: >=3.10,<4.0
Classifier: Programming Language :: Python :: 3
Classifier: Programming Language :: Python :: 3.10
Classifier: Programming Language :: Python :: 3.11
Requires-Dist: requests (>=2.31.0,<3.0.0)
